odoo/addons/stock_account_product_run_fifo_hook/README.rst
odoo/addons/stock_account_product_run_fifo_hook/__init__.py
odoo/addons/stock_account_product_run_fifo_hook/__manifest__.py
odoo/addons/stock_account_product_run_fifo_hook/hooks.py
odoo/addons/stock_account_product_run_fifo_hook/i18n/stock_account_product_run_fifo_hook.pot
odoo/addons/stock_account_product_run_fifo_hook/model/__init__.py
odoo/addons/stock_account_product_run_fifo_hook/model/product.py
odoo/addons/stock_account_product_run_fifo_hook/readme/CONTRIBUTORS.rst
odoo/addons/stock_account_product_run_fifo_hook/readme/DESCRIPTION.rst
odoo/addons/stock_account_product_run_fifo_hook/readme/USAGE.rst
odoo/addons/stock_account_product_run_fifo_hook/static/description/icon.png
odoo/addons/stock_account_product_run_fifo_hook/static/description/index.html
odoo14_addon_stock_account_product_run_fifo_hook-14.0.1.0.1.dist-info/METADATA
odoo14_addon_stock_account_product_run_fifo_hook-14.0.1.0.1.dist-info/WHEEL
odoo14_addon_stock_account_product_run_fifo_hook-14.0.1.0.1.dist-info/top_level.txt
odoo14_addon_stock_account_product_run_fifo_hook-14.0.1.0.1.dist-info/RECORD
